wisper/__init__.py
wisper/client.py
wisper/encryption.py
wisper/server.py
wisper/session.py
wisper/utils.py
wisper/aws/__init__.py
wisper/aws/api_gateway.py
wisper/aws/ec2.py
wisper/protobuf/__init__.py
wisper/protobuf/secure_message_pb2.py
wisper-1.0.0.dist-info/LICENSE
wisper-1.0.0.dist-info/METADATA
wisper-1.0.0.dist-info/WHEEL
wisper-1.0.0.dist-info/entry_points.txt
wisper-1.0.0.dist-info/top_level.txt
wisper-1.0.0.dist-info/RECORD
