Metadata-Version: 2.1
Name: wisper
Version: 1.0.0
Summary: Encrypted IRC
Home-page: https://github.com/parkerduckworth/wisper
Author: parkerduckworth
Author-email: parkerduckworth@gmail.com
License: MIT
Platform: UNKNOWN
Classifier: Development Status :: 5 - Production/Stable
Classifier: License :: OSI Approved :: MIT License
Classifier: Programming Language :: Python :: 2.7
Classifier: Topic :: Communications :: Chat :: Internet Relay Chat
Classifier: Environment :: Console
Classifier: Intended Audience :: End Users/Desktop
Classifier: Operating System :: POSIX
Requires-Dist: boto3
Requires-Dist: cryptography
Requires-Dist: protobuf
Requires-Dist: psutil
Requires-Dist: requests
Requires-Dist: werkzeug
